LICENSE
MANIFEST.in
README.md
setup.cfg
setup.py
rand_pass_generator/__init__.py
rand_pass_generator/generate.py
rand_pass_generator.egg-info/PKG-INFO
rand_pass_generator.egg-info/SOURCES.txt
rand_pass_generator.egg-info/dependency_links.txt
rand_pass_generator.egg-info/not-zip-safe
rand_pass_generator.egg-info/top_level.txt
rand_pass_generator/safe/LICENSE
rand_pass_generator/safe/README.rst
rand_pass_generator/safe/__init__.py
rand_pass_generator/safe/setup.py
rand_pass_generator/safe/test.py
rand_pass_generator/safe/safe/__init__.py
rand_pass_generator/safe/safe/_compat.py
rand_pass_generator/safe/safe/words.dat
test/test.py