Metadata-Version: 2.1
Name: rand-pass-generator
Version: 1.0.25
Summary: This module offers random password generator
Home-page: https://defartsa.dev/
Author: Deza Farras Tsany
Author-email: deza.ftsany@gmail.com
License: MIT
Download-URL: https://github.com/defartsa23/password-generator-py/archive/refs/heads/main.zip
Project-URL: Documentation, https://github.com/defartsa23/password-generator-py
Project-URL: Source, https://github.com/defartsa23/password-generator-py
Project-URL: Tracker, https://github.com/defartsa23/password-generator-py/issues
Keywords: PASSWORD,GENERATOR,RANDOM
Platform: UNKNOWN
Classifier: Development Status :: 5 - Production/Stable
Classifier: Intended Audience :: Developers
Classifier: Topic :: Software Development :: Build Tools
Classifier: License :: OSI Approved :: MIT License
Classifier: Programming Language :: Python :: 3 :: Only
Classifier: Operating System :: MacOS
Classifier: Operating System :: Microsoft
Classifier: Operating System :: Unix
